pylocaldatabase/__init__.py
pylocaldatabase/pylocaldatabase.py
pylocaldatabase-1.2.4.dist-info/LICENSE
pylocaldatabase-1.2.4.dist-info/METADATA
pylocaldatabase-1.2.4.dist-info/WHEEL
pylocaldatabase-1.2.4.dist-info/top_level.txt
pylocaldatabase-1.2.4.dist-info/RECORD
