Metadata-Version: 2.1
Name: pylocaldatabase
Version: 1.2.4
Summary: A package to simplify the use of json as a way to store data in Python.
Home-page: https://github.com/fortmea/python-local-database
Author: João Walter Amadeu
Author-email: joao.amadeu@unifio.edu.br
Project-URL: Bug Tracker, https://github.com/fortmea/python-local-database/issues
Classifier: Programming Language :: Python :: 3
Classifier: License :: OSI Approved :: MIT License
Classifier: Operating System :: OS Independent
Requires-Python: >=3.0
License-File: LICENSE
